<?xml version="1.0" encoding="UTF-8"?>
<beans xmlns='http://www.springframework.org/schema/beans'
xmlns:xsi='http://www.w3.org/2001/XMLSchema-instance'
xsi:schemaLocation='http://www.springframework.org/schema/beans
http://www.springframework.org/schema/beans/spring-beans.xsd'>
<!--
<bean id='persoonViewer' class='be.vdab.presentation.PersoonViewer'>
 	<property name='aantalKinderenTonen' value='TRUE'/> 
	<constructor-arg value='false'/>
<constructor-arg>
<list>
<value>VOORNAAM</value>
<value>FAMILIENAAM</value>
<value>AANTAL_KINDEREN</value>
</list>
</constructor-arg>
</bean>
-->

<bean id="persoonRepositoryCSV"
class="be.vdab.repositories.PersoonRepositoryCSV">
<constructor-arg value="E:/JosVdabOpleiding/Praktijk/Spring/personen.csv"/>
</bean>
<bean id="persoonRepositoryMeerdereRegels"
class="be.vdab.repositories.PersoonRepositoryMeerdereRegels">
<constructor-arg value="E:/JosVdabOpleiding/Praktijk/Spring/personen.txt"/>
</bean>
<bean id="persoonService" class="be.vdab.services.PersoonServiceImpl">
<constructor-arg ref="persoonRepositoryMeerdereRegels"/>
</bean>
<bean id="persoonViewer" class="be.vdab.presentation.PersoonViewer">
<constructor-arg>
<list>
<value>VOORNAAM</value>
<value>FAMILIENAAM</value>
<value>AANTAL_KINDEREN</value>
</list>
</constructor-arg>
<constructor-arg ref="persoonService"/>
</bean>
</beans>